[
  {
    "name": "Application Start",
    "start": 1541396140934,
    "end": 1541396149741,
    "duration": 8807,
    "pid": 59,
    "index": 0
  },
  {
    "name": "Load Plugin",
    "start": 1541396140958,
    "end": 1541396141159,
    "duration": 201,
    "pid": 59,
    "index": 1
  },
  {
    "name": "Load Config",
    "start": 1541396141160,
    "end": 1541396141381,
    "duration": 221,
    "pid": 59,
    "index": 2
  },
  {
    "name": "Require(0) config/config.default.js",
    "start": 1541396141165,
    "end": 1541396141170,
    "duration": 5,
    "pid": 59,
    "index": 3
  },
  {
    "name": "Require(1) node_modules/egg-session/config/config.default.js",
    "start": 1541396141182,
    "end": 1541396141185,
    "duration": 3,
    "pid": 59,
    "index": 4
  },
  {
    "name": "Require(2) node_modules/egg-security/config/config.default.js",
    "start": 1541396141189,
    "end": 1541396141195,
    "duration": 6,
    "pid": 59,
    "index": 5
  },
  {
    "name": "Require(3) node_modules/egg-jsonp/config/config.default.js",
    "start": 1541396141201,
    "end": 1541396141204,
    "duration": 3,
    "pid": 59,
    "index": 6
  },
  {
    "name": "Require(4) node_modules/egg-onerror/config/config.default.js",
    "start": 1541396141209,
    "end": 1541396141211,
    "duration": 2,
    "pid": 59,
    "index": 7
  },
  {
    "name": "Require(5) node_modules/egg-i18n/config/config.default.js",
    "start": 1541396141215,
    "end": 1541396141218,
    "duration": 3,
    "pid": 59,
    "index": 8
  },
  {
    "name": "Require(6) node_modules/egg-watcher/config/config.default.js",
    "start": 1541396141223,
    "end": 1541396141228,
    "duration": 5,
    "pid": 59,
    "index": 9
  },
  {
    "name": "Require(7) node_modules/egg-schedule/config/config.default.js",
    "start": 1541396141233,
    "end": 1541396141238,
    "duration": 5,
    "pid": 59,
    "index": 10
  },
  {
    "name": "Require(8) node_modules/egg-multipart/config/config.default.js",
    "start": 1541396141244,
    "end": 1541396141248,
    "duration": 4,
    "pid": 59,
    "index": 11
  },
  {
    "name": "Require(9) node_modules/egg-logrotator/config/config.default.js",
    "start": 1541396141258,
    "end": 1541396141277,
    "duration": 19,
    "pid": 59,
    "index": 12
  },
  {
    "name": "Require(10) node_modules/egg-static/config/config.default.js",
    "start": 1541396141283,
    "end": 1541396141287,
    "duration": 4,
    "pid": 59,
    "index": 13
  },
  {
    "name": "Require(11) node_modules/egg-view/config/config.default.js",
    "start": 1541396141294,
    "end": 1541396141298,
    "duration": 4,
    "pid": 59,
    "index": 14
  },
  {
    "name": "Require(12) node_modules/egg-validate/config/config.default.js",
    "start": 1541396141304,
    "end": 1541396141308,
    "duration": 4,
    "pid": 59,
    "index": 15
  },
  {
    "name": "Require(13) node_modules/egg-mongoose/config/config.default.js",
    "start": 1541396141313,
    "end": 1541396141316,
    "duration": 3,
    "pid": 59,
    "index": 16
  },
  {
    "name": "Require(14) node_modules/egg/config/config.default.js",
    "start": 1541396141319,
    "end": 1541396141323,
    "duration": 4,
    "pid": 59,
    "index": 17
  },
  {
    "name": "Require(15) config/config.default.js",
    "start": 1541396141332,
    "end": 1541396141332,
    "duration": 0,
    "pid": 59,
    "index": 18
  },
  {
    "name": "Require(16) node_modules/egg-static/config/config.prod.js",
    "start": 1541396141361,
    "end": 1541396141364,
    "duration": 3,
    "pid": 59,
    "index": 19
  },
  {
    "name": "Load extend/application.js",
    "start": 1541396141389,
    "end": 1541396141676,
    "duration": 287,
    "pid": 59,
    "index": 20
  },
  {
    "name": "Require(17) node_modules/egg-session/app/extend/application.js",
    "start": 1541396141398,
    "end": 1541396141403,
    "duration": 5,
    "pid": 59,
    "index": 21
  },
  {
    "name": "Require(18) node_modules/egg-security/app/extend/application.js",
    "start": 1541396141410,
    "end": 1541396141428,
    "duration": 18,
    "pid": 59,
    "index": 22
  },
  {
    "name": "Require(19) node_modules/egg-jsonp/app/extend/application.js",
    "start": 1541396141436,
    "end": 1541396141459,
    "duration": 23,
    "pid": 59,
    "index": 23
  },
  {
    "name": "Require(20) node_modules/egg-logrotator/app/extend/application.js",
    "start": 1541396141481,
    "end": 1541396141554,
    "duration": 73,
    "pid": 59,
    "index": 24
  },
  {
    "name": "Require(21) node_modules/egg-view/app/extend/application.js",
    "start": 1541396141559,
    "end": 1541396141580,
    "duration": 21,
    "pid": 59,
    "index": 25
  },
  {
    "name": "Load extend/request.js",
    "start": 1541396141676,
    "end": 1541396141848,
    "duration": 172,
    "pid": 59,
    "index": 26
  },
  {
    "name": "Require(22) node_modules/egg/app/extend/request.js",
    "start": 1541396141760,
    "end": 1541396141782,
    "duration": 22,
    "pid": 59,
    "index": 27
  },
  {
    "name": "Load extend/response.js",
    "start": 1541396141848,
    "end": 1541396141993,
    "duration": 145,
    "pid": 59,
    "index": 28
  },
  {
    "name": "Require(23) node_modules/egg/app/extend/response.js",
    "start": 1541396141902,
    "end": 1541396141932,
    "duration": 30,
    "pid": 59,
    "index": 29
  },
  {
    "name": "Load extend/context.js",
    "start": 1541396141993,
    "end": 1541396142600,
    "duration": 607,
    "pid": 59,
    "index": 30
  },
  {
    "name": "Require(24) node_modules/egg-security/app/extend/context.js",
    "start": 1541396142000,
    "end": 1541396142161,
    "duration": 161,
    "pid": 59,
    "index": 31
  },
  {
    "name": "Require(25) node_modules/egg-jsonp/app/extend/context.js",
    "start": 1541396142167,
    "end": 1541396142183,
    "duration": 16,
    "pid": 59,
    "index": 32
  },
  {
    "name": "Require(26) node_modules/egg-i18n/app/extend/context.js",
    "start": 1541396142191,
    "end": 1541396142194,
    "duration": 3,
    "pid": 59,
    "index": 33
  },
  {
    "name": "Require(27) node_modules/egg-multipart/app/extend/context.js",
    "start": 1541396142204,
    "end": 1541396142461,
    "duration": 257,
    "pid": 59,
    "index": 34
  },
  {
    "name": "Require(28) node_modules/egg-view/app/extend/context.js",
    "start": 1541396142472,
    "end": 1541396142482,
    "duration": 10,
    "pid": 59,
    "index": 35
  },
  {
    "name": "Require(29) node_modules/egg-validate/app/extend/context.js",
    "start": 1541396142488,
    "end": 1541396142494,
    "duration": 6,
    "pid": 59,
    "index": 36
  },
  {
    "name": "Require(30) node_modules/egg-mongoose/app/extend/context.js",
    "start": 1541396142500,
    "end": 1541396142503,
    "duration": 3,
    "pid": 59,
    "index": 37
  },
  {
    "name": "Require(31) node_modules/egg/app/extend/context.js",
    "start": 1541396142507,
    "end": 1541396142537,
    "duration": 30,
    "pid": 59,
    "index": 38
  },
  {
    "name": "Load extend/helper.js",
    "start": 1541396142600,
    "end": 1541396142892,
    "duration": 292,
    "pid": 59,
    "index": 39
  },
  {
    "name": "Require(32) node_modules/egg-security/app/extend/helper.js",
    "start": 1541396142611,
    "end": 1541396142795,
    "duration": 184,
    "pid": 59,
    "index": 40
  },
  {
    "name": "Require(33) node_modules/egg/app/extend/helper.js",
    "start": 1541396142835,
    "end": 1541396142839,
    "duration": 4,
    "pid": 59,
    "index": 41
  },
  {
    "name": "Load app.js",
    "start": 1541396142892,
    "end": 1541396143346,
    "duration": 454,
    "pid": 59,
    "index": 42
  },
  {
    "name": "Require(34) node_modules/egg-session/app.js",
    "start": 1541396142895,
    "end": 1541396142898,
    "duration": 3,
    "pid": 59,
    "index": 43
  },
  {
    "name": "Require(35) node_modules/egg-security/app.js",
    "start": 1541396142901,
    "end": 1541396142926,
    "duration": 25,
    "pid": 59,
    "index": 44
  },
  {
    "name": "Require(36) node_modules/egg-onerror/app.js",
    "start": 1541396142935,
    "end": 1541396143046,
    "duration": 111,
    "pid": 59,
    "index": 45
  },
  {
    "name": "Require(37) node_modules/egg-i18n/app.js",
    "start": 1541396143051,
    "end": 1541396143164,
    "duration": 113,
    "pid": 59,
    "index": 46
  },
  {
    "name": "Require(38) node_modules/egg-watcher/app.js",
    "start": 1541396143166,
    "end": 1541396143213,
    "duration": 47,
    "pid": 59,
    "index": 47
  },
  {
    "name": "Require(39) node_modules/egg-schedule/app.js",
    "start": 1541396143217,
    "end": 1541396143236,
    "duration": 19,
    "pid": 59,
    "index": 48
  },
  {
    "name": "Require(40) node_modules/egg-multipart/app.js",
    "start": 1541396143239,
    "end": 1541396143269,
    "duration": 30,
    "pid": 59,
    "index": 49
  },
  {
    "name": "Require(41) node_modules/egg-logrotator/app.js",
    "start": 1541396143275,
    "end": 1541396143279,
    "duration": 4,
    "pid": 59,
    "index": 50
  },
  {
    "name": "Require(42) node_modules/egg-static/app.js",
    "start": 1541396143284,
    "end": 1541396143289,
    "duration": 5,
    "pid": 59,
    "index": 51
  },
  {
    "name": "Require(43) node_modules/egg-validate/app.js",
    "start": 1541396143306,
    "end": 1541396143327,
    "duration": 21,
    "pid": 59,
    "index": 52
  },
  {
    "name": "Require(44) node_modules/egg-mongoose/app.js",
    "start": 1541396143333,
    "end": 1541396143336,
    "duration": 3,
    "pid": 59,
    "index": 53
  },
  {
    "name": "Before Start in node_modules/egg-watcher/lib/init.js:15:14",
    "start": 1541396143417,
    "end": 1541396149697,
    "duration": 6280,
    "pid": 59,
    "index": 54
  },
  {
    "name": "Before Start in node_modules/egg-mongoose/lib/mongoose.js:77:7",
    "start": 1541396148221,
    "end": 1541396149740,
    "duration": 1519,
    "pid": 59,
    "index": 55
  },
  {
    "name": "Before Start in node_modules/egg-mongoose/lib/mongoose.js:42:9",
    "start": 1541396148221,
    "end": 1541396149647,
    "duration": 1426,
    "pid": 59,
    "index": 56
  },
  {
    "name": "Load Service",
    "start": 1541396148222,
    "end": 1541396148304,
    "duration": 82,
    "pid": 59,
    "index": 57
  },
  {
    "name": "Load \"service\" to Context",
    "start": 1541396148222,
    "end": 1541396148304,
    "duration": 82,
    "pid": 59,
    "index": 58
  },
  {
    "name": "Load Middleware",
    "start": 1541396148304,
    "end": 1541396149483,
    "duration": 1179,
    "pid": 59,
    "index": 59
  },
  {
    "name": "Load \"middlewares\" to Application",
    "start": 1541396148305,
    "end": 1541396149340,
    "duration": 1035,
    "pid": 59,
    "index": 60
  },
  {
    "name": "Load Controller",
    "start": 1541396149484,
    "end": 1541396149545,
    "duration": 61,
    "pid": 59,
    "index": 61
  },
  {
    "name": "Load \"controller\" to Application",
    "start": 1541396149484,
    "end": 1541396149545,
    "duration": 61,
    "pid": 59,
    "index": 62
  },
  {
    "name": "Load Router",
    "start": 1541396149546,
    "end": 1541396149560,
    "duration": 14,
    "pid": 59,
    "index": 63
  },
  {
    "name": "Require(45) app/router.js",
    "start": 1541396149550,
    "end": 1541396149554,
    "duration": 4,
    "pid": 59,
    "index": 64
  },
  {
    "name": "Before Start in node_modules/egg-core/lib/egg.js:287:10",
    "start": 1541396149555,
    "end": 1541396149647,
    "duration": 92,
    "pid": 59,
    "index": 65
  },
  {
    "name": "Load \"model\" to Application",
    "start": 1541396149601,
    "end": 1541396149645,
    "duration": 44,
    "pid": 59,
    "index": 66
  }
]